purl2notices/__init__.py
purl2notices/__main__.py
purl2notices/cache.py
purl2notices/cli.py
purl2notices/config.py
purl2notices/constants.py
purl2notices/core.py
purl2notices/formatter.py
purl2notices/models.py
purl2notices/overrides.py
purl2notices/scanner.py
purl2notices/utils.py
purl2notices/validators.py
purl2notices/data/licenses/0BSD.txt
purl2notices/data/licenses/3D-Slicer-1.0.txt
purl2notices/data/licenses/AAL.txt
purl2notices/data/licenses/ADSL.txt
purl2notices/data/licenses/AFL-1.1.txt
purl2notices/data/licenses/AFL-1.2.txt
purl2notices/data/licenses/AFL-2.0.txt
purl2notices/data/licenses/AFL-2.1.txt
purl2notices/data/licenses/AFL-3.0.txt
purl2notices/data/licenses/AGPL-1.0-only.txt
purl2notices/data/licenses/AGPL-1.0-or-later.txt
purl2notices/data/licenses/AGPL-1.0.txt
purl2notices/data/licenses/AGPL-3.0-only.txt
purl2notices/data/licenses/AGPL-3.0-or-later.txt
purl2notices/data/licenses/AGPL-3.0.txt
purl2notices/data/licenses/AMD-newlib.txt
purl2notices/data/licenses/AMDPLPA.txt
purl2notices/data/licenses/AML-glslang.txt
purl2notices/data/licenses/AML.txt
purl2notices/data/licenses/AMPAS.txt
purl2notices/data/licenses/ANTLR-PD-fallback.txt
purl2notices/data/licenses/ANTLR-PD.txt
purl2notices/data/licenses/APAFML.txt
purl2notices/data/licenses/APL-1.0.txt
purl2notices/data/licenses/APSL-1.0.txt
purl2notices/data/licenses/APSL-1.1.txt
purl2notices/data/licenses/APSL-1.2.txt
purl2notices/data/licenses/APSL-2.0.txt
purl2notices/data/licenses/ASWF-Digital-Assets-1.0.txt
purl2notices/data/licenses/ASWF-Digital-Assets-1.1.txt
purl2notices/data/licenses/Abstyles.txt
purl2notices/data/licenses/AdaCore-doc.txt
purl2notices/data/licenses/Adobe-2006.txt
purl2notices/data/licenses/Adobe-Display-PostScript.txt
purl2notices/data/licenses/Adobe-Glyph.txt
purl2notices/data/licenses/Adobe-Utopia.txt
purl2notices/data/licenses/Afmparse.txt
purl2notices/data/licenses/Aladdin.txt
purl2notices/data/licenses/Apache-1.0.txt
purl2notices/data/licenses/Apache-1.1.txt
purl2notices-1.2.7.dist-info/licenses/AUTHORS.md
purl2notices-1.2.7.dist-info/licenses/LICENSE
purl2notices-1.2.7.dist-info/METADATA
purl2notices-1.2.7.dist-info/WHEEL
purl2notices-1.2.7.dist-info/entry_points.txt
purl2notices-1.2.7.dist-info/top_level.txt
purl2notices-1.2.7.dist-info/RECORD
