Metadata-Version: 2.4
Name: purl2notices
Version: 1.2.7
Summary: Generate legal notices (attribution to authors and copyrights) for software packages
Author-email: Oscar Valenzuela B <oscar.valenzuela.b@gmail.com>
License: Apache-2.0
Project-URL: Homepage, https://github.com/SemClone/purl2notices
Project-URL: Repository, https://github.com/SemClone/purl2notices
Project-URL: Issues, https://github.com/SemClone/purl2notices/issues
Keywords: sbom,license,copyright,attribution,purl,package-url,legal-notices,compliance
Classifier: Development Status :: 3 - Alpha
Classifier: Intended Audience :: Developers
Classifier: License :: OSI Approved :: Apache Software License
Classifier: Operating System :: OS Independent
Classifier: Programming Language :: Python :: 3
Classifier: Programming Language :: Python :: 3.8
Classifier: Programming Language :: Python :: 3.9
Classifier: Programming Language :: Python :: 3.10
Classifier: Programming Language :: Python :: 3.11
Classifier: Programming Language :: Python :: 3.12
Classifier: Topic :: Software Development :: Libraries :: Python Modules
Classifier: Topic :: Software Development :: Build Tools
Classifier: Topic :: System :: Software Distribution
Requires-Python: >=3.8
License-File: LICENSE
License-File: AUTHORS.md
Requires-Dist: click>=8.0.0
Requires-Dist: jinja2>=3.0.0
Requires-Dist: aiohttp>=3.8.0
Requires-Dist: aiofiles>=0.8.0
Requires-Dist: packageurl-python>=0.11.0
Requires-Dist: purl2src>=1.2.3
Requires-Dist: upmex>=1.5.0
Requires-Dist: osslili>=1.3.0
Requires-Dist: python-Levenshtein>=0.20.0
Requires-Dist: pyyaml>=6.0
Requires-Dist: python-magic>=0.4.27
Requires-Dist: tqdm>=4.65.0
Requires-Dist: jsonschema>=4.17.0
Requires-Dist: platformdirs>=3.0.0
Requires-Dist: tomli>=2.0.0; python_version < "3.11"
Requires-Dist: requests>=2.28.0
Provides-Extra: dev
Requires-Dist: pytest>=7.0.0; extra == "dev"
Requires-Dist: pytest-asyncio>=0.21.0; extra == "dev"
Requires-Dist: pytest-cov>=4.0.0; extra == "dev"
Requires-Dist: pytest-mock>=3.10.0; extra == "dev"
Requires-Dist: black>=23.0.0; extra == "dev"
Requires-Dist: ruff>=0.1.0; extra == "dev"
Requires-Dist: mypy>=1.0.0; extra == "dev"
Requires-Dist: types-aiofiles; extra == "dev"
Requires-Dist: types-pyyaml; extra == "dev"
Requires-Dist: types-tqdm; extra == "dev"
Requires-Dist: build>=0.10.0; extra == "dev"
Requires-Dist: twine>=4.0.0; extra == "dev"
Dynamic: license-file
